pyinfuse/__init__.py
pyinfuse/__main__.py
pyinfuse/py.typed
pyinfuse/pyinfuse.py
pyinfuse-0.1.2.dist-info/LICENSE
pyinfuse-0.1.2.dist-info/METADATA
pyinfuse-0.1.2.dist-info/WHEEL
pyinfuse-0.1.2.dist-info/entry_points.txt
pyinfuse-0.1.2.dist-info/RECORD
