Metadata-Version: 2.1
Name: pyinfuse
Version: 0.1.2
Summary: Pyinfuse
Home-page: https://github.com/nanosystemslab/pyinfuse
License: MIT
Author: Nanosystems Lab
Author-email: fnslab@hawaii.edu
Requires-Python: >=3.9,<4.0
Classifier: Development Status :: 5 - Production/Stable
Classifier: License :: OSI Approved :: MIT License
Classifier: Programming Language :: Python :: 3
Classifier: Programming Language :: Python :: 3.9
Classifier: Programming Language :: Python :: 3.10
Classifier: Programming Language :: Python :: 3.11
Classifier: Programming Language :: Python :: 3.12
Requires-Dist: click (>=8.1.7,<9.0.0)
Requires-Dist: pyserial (>=3.5,<4.0)
Requires-Dist: types-pyserial (>=3.5.0.20240826,<4.0.0.0)
Project-URL: Changelog, https://github.com/nanosystemslab/pyinfuse/releases
Project-URL: Documentation, https://pyinfuse.readthedocs.io
Project-URL: Repository, https://github.com/nanosystemslab/pyinfuse
